securepip/__init__.py
securepip/cli.py
securepip/core.py
securepypy-0.2.0.dist-info/METADATA
securepypy-0.2.0.dist-info/WHEEL
securepypy-0.2.0.dist-info/entry_points.txt
securepypy-0.2.0.dist-info/top_level.txt
securepypy-0.2.0.dist-info/RECORD
