Metadata-Version: 2.1
Name: securepypy
Version: 0.2.0
Summary: A security-focused package installer and analyzer for Python
Home-page: https://github.com/gnubyte/securepip
Author: Patrick Hastings
Author-email: phastings@openmobo.com
License: UNKNOWN
Platform: UNKNOWN
Classifier: Development Status :: 3 - Alpha
Classifier: Intended Audience :: Developers
Classifier: License :: OSI Approved :: MIT License
Classifier: Programming Language :: Python :: 3
Classifier: Programming Language :: Python :: 3.9
Requires-Python: >=3.9
Requires-Dist: requests>=2.31.0
Requires-Dist: urllib3<2.0.0
Requires-Dist: packaging>=23.2
Requires-Dist: colorama>=0.4.6
Requires-Dist: tqdm>=4.66.1
Requires-Dist: pyyaml>=6.0.1
